vmm/__init__.py
vmm/vmm.py
vmm-0.1.7.dist-info/METADATA
vmm-0.1.7.dist-info/WHEEL
vmm-0.1.7.dist-info/RECORD
